LICENSE
MANIFEST.in
setup.py
requests_runscope/__init__.py
requests_runscope/__init__.pyc
requests_runscope/runscope_adapter.py
requests_runscope/runscope_adapter.pyc
requests_runscope.egg-info/PKG-INFO
requests_runscope.egg-info/SOURCES.txt
requests_runscope.egg-info/dependency_links.txt
requests_runscope.egg-info/top_level.txt