Metadata-Version: 1.1
Name: requests-runscope
Version: 0.1.6
Summary: This package adds Runscope support to the Python Requests library.
Home-page: https://github.com/Runscope/requests-runscope
Author: Runscope Inc.
Author-email: help@runscope.com
License: Copyright (c) 2013 Runscope Inc.
